thunkmetrc/__init__.py
thunkmetrc/client/__init__.py
thunkmetrc/client/client.py
thunkmetrc_client-0.2.2.dist-info/METADATA
thunkmetrc_client-0.2.2.dist-info/WHEEL
thunkmetrc_client-0.2.2.dist-info/RECORD
