Metadata-Version: 2.4
Name: thunkmetrc-client
Version: 0.2.2
Summary: Auto-generated Python client for ThunkMetrc
Project-URL: Documentation, https://github.com/thunkmetrc/sdks#readme
Project-URL: Issues, https://github.com/thunkmetrc/sdks/issues
Project-URL: Source, https://github.com/thunkmetrc/sdks
Author-email: ThunkMetrc <dev@thunkmetrc.com>
License-Expression: MIT
Classifier: Development Status :: 4 - Beta
Classifier: Programming Language :: Python
Classifier: Programming Language :: Python :: 3.10
Classifier: Programming Language :: Python :: 3.11
Classifier: Programming Language :: Python :: Implementation :: CPython
Classifier: Programming Language :: Python :: Implementation :: PyPy
Requires-Python: >=3.10
Requires-Dist: httpx>=0.24.0
